xstrip_auth/__init__.py
xtrip_auth/__init__.py
xstrip_auth-0.2.1.dist-info/LICENSE
xstrip_auth-0.2.1.dist-info/METADATA
xstrip_auth-0.2.1.dist-info/WHEEL
xstrip_auth-0.2.1.dist-info/top_level.txt
xstrip_auth-0.2.1.dist-info/RECORD
