Metadata-Version: 2.1
Name: xstrip-auth
Version: 0.2.1
Summary: Cryptographically strong pseudorandom key generator based on the XStrip Algorithm
Home-page: https://github.com/miraclx/xstrip_auth
Author: Miraculous Owonubi
Author-email: omiraculous@gmail.com
License: Apache-2.0
Platform: UNKNOWN
Classifier: Operating System :: OS Independent
Classifier: Programming Language :: Python :: 3
Classifier: License :: OSI Approved :: Apache Software License
